MANIFEST.in
README.txt
setup.cfg
setup.py
docs/HISTORY.txt
horae/__init__.py
horae.subscription.egg-info/PKG-INFO
horae.subscription.egg-info/SOURCES.txt
horae.subscription.egg-info/dependency_links.txt
horae.subscription.egg-info/entry_points.txt
horae.subscription.egg-info/namespace_packages.txt
horae.subscription.egg-info/not-zip-safe
horae.subscription.egg-info/requires.txt
horae.subscription.egg-info/top_level.txt
horae/subscription/__init__.py
horae/subscription/configure.zcml
horae/subscription/interfaces.py
horae/subscription/permissions.py
horae/subscription/subscription.py
horae/subscription/viewlets.py
horae/subscription/locales/horae.subscription.pot
horae/subscription/locales/de/LC_MESSAGES/horae.subscription.mo
horae/subscription/locales/de/LC_MESSAGES/horae.subscription.po
horae/subscription/viewlet_templates/subscribers.cpt