Metadata-Version: 1.0
Name: horae.subscription
Version: 1.0a1
Summary: Provides functionality to subscribe to an object
Home-page: UNKNOWN
Author: Simon Kaeser
Author-email: skaeser@gmail.com
License: GPL
Platform: UNKNOWN
Classifier: Programming Language :: Python
